setup.py
mjpeg_tools.egg-info/PKG-INFO
mjpeg_tools.egg-info/SOURCES.txt
mjpeg_tools.egg-info/dependency_links.txt
mjpeg_tools.egg-info/requires.txt
mjpeg_tools.egg-info/top_level.txt
mjpegtools/__init__.py