Metadata-Version: 1.1
Name: mjpeg-tools
Version: 0.0.6
Summary: mjpeg client, server and manipulator
Home-page: https://github.com/royendgel
Author: Royendgel Silberie
Author-email: royendgel@techprocur.com
License: UNKNOWN
Keywords: mjpegtools mjpeg jpeg
Platform: UNKNOWN
Classifier: Operating System :: MacOS :: MacOS X
Classifier: Operating System :: Unix
Classifier: Development Status :: 3 - Alpha
Classifier: Topic :: Utilities
Classifier: Programming Language :: Python :: 2.7
